ezFraction/__init__.py
ezFraction-1.0.0.dist-info/LICENSE
ezFraction-1.0.0.dist-info/METADATA
ezFraction-1.0.0.dist-info/WHEEL
ezFraction-1.0.0.dist-info/top_level.txt
ezFraction-1.0.0.dist-info/RECORD
