Metadata-Version: 2.1
Name: ezFraction
Version: 1.0.0
Summary: Fractions made easy
Home-page: https://github.com/GooDeeJaY/ezFraction
Author: Jasur Yusupov
Author-email: jasuryusupov14@gmail.com
License: MIT
Project-URL: Bug Tracker, https://github.com/GooDeeJaY/ezFraction/issues
Platform: UNKNOWN
Classifier: Programming Language :: Python :: 3
Classifier: License :: OSI Approved :: MIT License
Classifier: Operating System :: OS Independent
Requires-Python: >=3.6
